css_for_ctk/__about__.py
css_for_ctk/__init__.py
css_for_ctk/apply.py
css_for_ctk/example.py
css_for_ctk/parse.py
css_for_ctk/style.css
css_for_ctk-0.0.2.dist-info/METADATA
css_for_ctk-0.0.2.dist-info/WHEEL
css_for_ctk-0.0.2.dist-info/licenses/LICENSE.txt
css_for_ctk-0.0.2.dist-info/RECORD
